{
  "name": "2024-10-25-02-51-13-103",
  "cls": "医学伦理学",
  "numb": "55",
  "unit": "第四章 医学伦理规范体系",
  "test": "女医生让男医学生回避是实现了患者的",
  "option": [
    "A.尊重的需要",
    "B.安全的需要",
    "C.生理的需要",
    "D.社会交往的需要",
    "E.归属和爱的需要"
  ],
  "answer": "A",
  "point": "（5版医学伦理学P34）“尊重原则要求医务人员尊重患者。欧美一般称为自主原则，即对自主的人及其自主性的尊重。知情同意、知情选择、要求保守秘密和隐私等均是尊重患者（A对）的体现。广义上的尊重原则还包括医务人员尊重患者及其家属的人格”。",
  "discuss": "青年女性，因乳房刺痛来医院就诊，诊室内除了一个女医生外还有一个男医学生，女医生未开口问诊，在让男医学生回避后才开始对患者问诊和查体。女医生让男医学生回避是实现了对患者的尊重原则。尊重患者的隐私，主要包括两方面内容：一是个人的私密性信息不被泄露，二是身体不被随意观察（A对）。"
}