{
  "name": "2024-10-25-02-56-23-698",
  "cls": "医学伦理学",
  "numb": "27",
  "unit": "第七章 临床常规诊治伦理",
  "test": "案例医生决策需首要遵守的医学伦理原则是",
  "option": [
    "A.公正原则",
    "B.尊重原则",
    "C.有利原则",
    "D.公益原则",
    "E.不伤害原则"
  ],
  "answer": "C",
  "point": "（5版医学伦理学P36）“有利原则要求医务人员：①首先考虑患者的利益，做对患者有益的事，努力维护患者的生命健康，当患者利益与科学利益、医生利益发生冲突时，应该将患者的利益放在首位”（C对）。",
  "discuss": "一孕妇得知自己怀孕很开心，但出于工作原因并且自己想再奋斗，打算人工流产，但丈夫和婆婆都不同意，孕妇很犹豫。目前该孕妇处于犹豫阶段，未作决定，医生决策需首要遵守有利原则（C对）。医学道德基本原则有不伤害原则、有利原则、尊重原则、公正原则。其中，有利原则是指把有利于病人健康放在第一位并切实为其谋利益的伦理原则。尊重原则主要包括尊重病人的生命、人格、隐私权、自主权及处理好相关的一些特殊问题。若该孕妇已做出决定，医生的决策需遵守尊重原则（B错）。公正原则是指形式公正和内容公正的有机统一为依据分配和实现医疗和健康礼仪的伦理原则（A错）。不伤害原则是指医务人员的整个医疗行为中，无论动机，还是效果，均应避免对病人造成伤害（E错）。医学道德基本原则不包括公益原则（D错）。"
}