{
  "name": "2024-10-21-06-07-30-593",
  "cls": "医学心理学",
  "numb": "44",
  "unit": "第十章 病人心理",
  "test": "患者求医类型",
  "option": [
    "A.主动就诊",
    "B.被动就诊",
    "C.家人强迫",
    "D.医师转介",
    "E.强制就医"
  ],
  "answer": "A",
  "point": "（7版医学心理学P161）“主动求医行为是指人们为治疗疾病、维护健康而主动寻求医疗帮助的行为，多数人会采取主动求医行为”（A对）。",
  "discuss": "青年男性，因不受控制的想杀死自己妻子（强迫行为），害怕伤害妻子（违反自己意愿，但无法摆脱），产生罪恶感，来心理门诊就诊（属于主动求医类型），心理医师认为，该患者的强迫症状导致，杀害妻子可能性不大，但又担心该患者伤害其妻子，建议其进行药物治疗和心理治疗。其求医类型属于主动就诊（A对CD错）。被动就诊（B错）多为未成年、意识丧失、老年人等由监护人送来。强制就医（E错）多为精神病、传染病强制性治疗。"
}