{
  "name": "2024-09-24-17-57-07-464",
  "cls": "儿科学",
  "numb": "133",
  "unit": "第十二章 泌尿系统疾病",
  "test": "若患儿突然出现肉眼血尿伴腰痛，最可能并发",
  "option": [
    "A.肾静脉血栓",
    "B.间质性肾炎",
    "C.肾衰竭",
    "D.肾结石",
    "E.泌尿系感染"
  ],
  "answer": "A",
  "point": "（P302）“1.感染 肾病患儿极易罹患各种感染。常见为呼吸道、皮肤、泌尿道感染和原发性腹膜炎等，其中尤以上呼吸道感染最多见，占50%以上。呼吸道感染中病毒感染常见。细菌感染中以肺炎链球菌为主，结核分枝杆菌感染亦应引起重视。另外，肾病患儿的医院内感染不容忽视，以呼吸道感染和泌尿道感染（E错）最多见，致病菌以条件致病菌为主。2.电解质紊乱和低血容量 常见的电解质紊乱有低钠、低钾及低钙血症。患儿不恰当长期禁用食盐或长期食用不含钠的食盐代用品、过多使用利尿剂以及感染、呕吐、腹泻等因素均可致低钠血症。其临床表现可有厌食、乏力、懒言、嗜睡、血压下降甚至出现休克、抽搐等。另外由于低蛋白血症、血浆胶体渗透压下降、显著水肿而常有血容量不足，尤其在各种诱因引起低钠血症时易出现低血容量性休克。3.血栓形成 肾病综合征高凝状态易致各种动、静脉血栓形成，以肾静脉血栓形成常见（A对），表现为突发腰痛、出现血尿或血尿加重、少尿，甚至发生肾衰竭。以不同部位血管血栓形成的亚临床型更多见…4.急性肾衰竭（C错） 5%的微小病变型肾病可并发急性肾衰竭。5.肾小管功能障碍 除原有肾小球的基础病变可引起肾小管功能损害外，由于大量尿蛋白的重吸收，可导致肾小管（主要是近曲小管）功能损害，出现肾性糖尿或氨基酸尿”。",
  "discuss": "女孩，9岁。水肿1个月。查体：BP135/95mmHg，颜面和四肢明显水肿。实验室检查：尿蛋白（+++），24小时尿蛋白定量2.5g，血浆白蛋白28g/L，尿素氮10mmol/L，血补体C30.65g/L。患儿，血浆白蛋白28g/L（低于30g/L），应诊断为肾病综合征。在此基础上突然出现肉眼血尿伴腰痛，说明该患儿并发了肾静脉血栓（A对）。肾病综合征主要并发的是近曲小管吸收障碍类的病变，而不是间质性肾炎（B错）。并发肾衰竭的情况一般不多见，且会有全身其他系统的病变，临床症状很严重（C错）。肾结石不属于肾病综合征的并发症（D错）。泌尿系感染也会有肉眼血尿伴腰痛的变现，但一般此症状是缓慢的出现，而不是突发，之所以会突发是因为血栓突然的将肾静脉阻塞（E错）。"
}