{
  "name": "2024-09-24-16-57-21-261",
  "cls": "儿科学",
  "numb": "5",
  "unit": "第十章 呼吸系统疾病",
  "test": "病因应首先考虑",
  "option": [
    "A.腭扁桃体肿大",
    "B.鼻炎",
    "C.咽扁桃体肿大",
    "D.鼻窦炎",
    "E.喉炎"
  ],
  "answer": "C",
  "point": "（P238）“扁桃体包括腭扁桃体和咽扁桃体，腭扁桃体1岁末逐渐增大，4～10岁发育达高峰，14～15岁时渐退化，故腭扁桃体炎常见于年长儿，婴儿则少见（A错）。咽扁桃体又称腺样体，6个月已发育，位于鼻咽顶部与后壁交界处，严重的腺样体肥大是小儿阻塞性睡眠呼吸暂停综合征的重要原因（C对）”。",
  "discuss": "患儿1岁，睡眠打鼾，侧卧好转，感冒时加重。最可能的诊断为阻塞性睡眠综合征，病因首先考虑咽扁桃体肿大（C对）。咽扁桃体又称腺样体，6个月已发育，位于鼻咽顶部与后壁交界处，严重的腺样体肥大是小儿阻塞性睡眠呼吸暂停综合征的重要原因。鼻炎（B错）、鼻窦炎（D错）主要表现为流涕、打喷嚏。临床常见的扁桃体炎为腭扁桃体炎，幼儿腭扁桃体1岁开始发育，4～10岁发育达高峰，15岁前逐渐缩小。患儿1岁，腭扁桃体未发育，故不选（A错）。喉炎（E错）以犬吠样咳嗽、声嘶、吸气性呼吸困难为临床特征。轻微炎症即可引起喉头狭窄致吸气性呼吸困难（P242）。"
}