{
  "name": "2024-09-24-16-51-05-836",
  "cls": "儿科学",
  "numb": "74",
  "unit": "第九章 消化系统疾病",
  "test": "第一天补液总量和张力应为",
  "option": [
    "A.720ml，1/2张",
    "B.1040ml，1/2张",
    "C.1100ml，2/3张",
    "D.1200ml，2/3张",
    "E.1400ml，2/3张"
  ],
  "answer": "B",
  "point": "（三版八年制儿科学P23）“第1天补液总量轻度脱水为90～120ml/kg，中度脱水为120～150ml/kg，重度脱水为150～180ml/kg”。（P45）“等渗性脱水时血清钠在130～150mmol/L”。（P52）“通常对低渗性脱水补2/3张含钠液；等渗性脱水补1/2张含钠液；高渗性脱水补1/3-1/5张含钠液，如临床上判断脱水性质有困难，可先按等渗性脱水处理”（B对）。",
  "discuss": "该患儿有腹泻的病史，并且有尿量明显少、精神萎靡、皮肤弹性差、眼凹陷、四肢凉的临床表现，应诊断为中度脱水，该患儿血钠132mmol/L，应诊断为等渗性脱水，综上该患儿为中度等渗性脱水，通常等渗性脱水应选择1/2张液，中度脱水第一天为120～150ml/kg，该患儿体重是8kg，所以补液总量960～1200ml（B对）。"
}